.DS_Store
absolutlynothing/__init__.py
absolutlynothing-1.1.1.dist-info/METADATA
absolutlynothing-1.1.1.dist-info/WHEEL
absolutlynothing-1.1.1.dist-info/top_level.txt
absolutlynothing-1.1.1.dist-info/RECORD
