Metadata-Version: 2.1
Name: absolutlynothing
Version: 1.1.1
Summary: Nothing
Home-page: UNKNOWN
Author: Nathan Adams
License: UNKNOWN
Platform: UNKNOWN
Classifier: Programming Language :: Python :: 3
Classifier: License :: OSI Approved :: MIT License
Classifier: Operating System :: OS Independent
Requires-Python: >=3.6
